qanom/__init__.py
qanom/config.py
qanom/evaluate.py
qanom/extract_candidates.py
qanom/nominalization_detector.py
qanom/qanom_end_to_end_pipeline.py
qanom/qasrl_seq2seq_pipeline.py
qanom/utils.py
qanom/version.txt
qanom/annotations/__init__.py
qanom/annotations/analyze.py
qanom/annotations/common.py
qanom/annotations/consolidation.py
qanom/annotations/decode_encode_answers.py
qanom/annotations/post_processing.py
qanom/annotations/qasrlv2_jsonl.py
qanom/candidate_extraction/__init__.py
qanom/candidate_extraction/cand_utils.py
qanom/candidate_extraction/candidate_extraction.py
qanom/candidate_extraction/catvar.py
qanom/candidate_extraction/verb_to_nom.py
qanom/candidate_extraction/wordnet_util.py
qanom/evaluation/__init__.py
qanom/evaluation/alignment.py
qanom/evaluation/evaluate.py
qanom/evaluation/evaluate_inter_annotator.py
qanom/evaluation/evaluate_worker.py
qanom/evaluation/metrics.py
qanom/evaluation/roles.py
qanom/resources/catvar/LICENSE.txt
qanom/resources/catvar/README.md
qanom/resources/catvar/catvar21.signed
qanom/resources/verb-to-nom-heuristic/nom_verb_pairs.txt
qanom-0.0.21.dist-info/LICENSE
qanom-0.0.21.dist-info/METADATA
qanom-0.0.21.dist-info/WHEEL
qanom-0.0.21.dist-info/top_level.txt
qanom-0.0.21.dist-info/RECORD
