Metadata-Version: 2.1
Name: qanom
Version: 0.0.21
Summary: package for Question-Answer driven Semantic Role Labeling for Nominalizations (QANom)
Home-page: https://github.com/kleinay/QANom
Author: Ayal Klein
Author-email: ayal.s.klein@gmail.com
License: UNKNOWN
Platform: UNKNOWN
Classifier: Programming Language :: Python :: 3
Classifier: License :: OSI Approved :: MIT License
Classifier: Operating System :: OS Independent
Requires-Python: >=3.7
Requires-Dist: transformers (>=2.11.0)
Requires-Dist: torch (>=1.4)
Requires-Dist: nltk
Requires-Dist: pandas
Requires-Dist: tqdm
Requires-Dist: sklearn
